wheel2deb/__init__.py
wheel2deb/__main__.py
wheel2deb/apt.py
wheel2deb/build.py
wheel2deb/cli.py
wheel2deb/context.py
wheel2deb/debian.py
wheel2deb/depends.py
wheel2deb/logger.py
wheel2deb/pydist.py
wheel2deb/pyvers.py
wheel2deb/templates.py
wheel2deb/utils.py
wheel2deb/version.py
wheel2deb-0.9.5.dist-info/LICENSE
wheel2deb-0.9.5.dist-info/METADATA
wheel2deb-0.9.5.dist-info/WHEEL
wheel2deb-0.9.5.dist-info/entry_points.txt
wheel2deb-0.9.5.dist-info/RECORD
