Metadata-Version: 2.1
Name: wheel2deb
Version: 0.9.5
Summary: Python wheel to debian package converter
Home-page: https://github.com/upciti/wheel2deb
License: MIT
Keywords: Debian,DevOps,Automation,converter,package
Author: Upciti
Author-email: support@upciti.com
Requires-Python: >=3.10,<3.13
Classifier: Development Status :: 3 - Alpha
Classifier: Intended Audience :: Developers
Classifier: License :: OSI Approved :: MIT License
Classifier: Programming Language :: Python :: 3
Classifier: Programming Language :: Python :: 3.10
Classifier: Programming Language :: Python :: 3.11
Classifier: Programming Language :: Python :: 3.12
Classifier: Topic :: Software Development :: Code Generators
Provides-Extra: pyinstaller
Requires-Dist: Jinja2 (>=3,<4)
Requires-Dist: PyYAML
Requires-Dist: attrs (>=20.1)
Requires-Dist: colorama
Requires-Dist: dirsync
Requires-Dist: packaging
Requires-Dist: pkginfo
Requires-Dist: pyinstaller ; extra == "pyinstaller"
Requires-Dist: rich
Requires-Dist: typer (>=0.6.1)
Requires-Dist: wheel
Project-URL: Repository, https://github.com/upciti/wheel2deb
